MANIFEST.in
README.md
VERSION
requirements.txt
setup.py
plecost.egg-info/PKG-INFO
plecost.egg-info/SOURCES.txt
plecost.egg-info/dependency_links.txt
plecost.egg-info/entry_points.txt
plecost.egg-info/requires.txt
plecost.egg-info/top_level.txt
plecost_lib/__init__.py
plecost_lib/api.py
plecost_lib/plecost.py
plecost_lib/libs/__init__.py
plecost_lib/libs/data.py
plecost_lib/libs/db.py
plecost_lib/libs/exceptions.py
plecost_lib/libs/helpers.py
plecost_lib/libs/htaccess.py
plecost_lib/libs/plugins_utils.py
plecost_lib/libs/reporters.py
plecost_lib/libs/utils.py
plecost_lib/libs/versions.py
plecost_lib/libs/wordlist.py
plecost_lib/libs/updaters/__init__.py
plecost_lib/libs/updaters/cves.py
plecost_lib/libs/updaters/plugins.py
plecost_lib/resources/cve.db
plecost_lib/resources/plugin_list_10.txt
plecost_lib/resources/plugin_list_100.txt
plecost_lib/resources/plugin_list_1000.txt
plecost_lib/resources/plugin_list_250.txt
plecost_lib/resources/plugin_list_50.txt
plecost_lib/resources/plugin_list_huge.txt
plecost_lib/resources/wordpress_detection.txt