Metadata-Version: 1.1
Name: plecost
Version: 1.1.2
Summary: Wordpress finger printer tool and vulnerabilities searcher
Home-page: https://github.com/iniqua/plecost/tree/python3
Author: Plecost team
Author-email: plecost@iniqua.com
License: GPL2
Platform: UNKNOWN
Classifier: Environment :: Console
Classifier: Intended Audience :: System Administrators
Classifier: Intended Audience :: Other Audience
Classifier: License :: OSI Approved :: BSD License
Classifier: Operating System :: MacOS
Classifier: Operating System :: Microsoft :: Windows
Classifier: Operating System :: POSIX
Classifier: Programming Language :: Python :: 3
Classifier: Topic :: Security
